[
    {
        "student": "Jerry",
        "class": "Y8",
        "lesson": "Unit 2 - Lesson 1: Everyday Objects",
        "activity": "Lesson completed",
        "answer": {
            "inputScore": 2,
            "vocabularyScore": 0,
            "grammarScore": 0,
            "comprehensionScore": 2
        },
        "responses": {
            "inputAnswers": {
                "0": "Why everyday objects are important",
                "1": "Famous inventions and machines",
                "2": "They are becoming more environmentally friendly"
            },
            "vocabularyAnswers": {
                "0": "invent",
                "1": "routines",
                "2": "routine",
                "3": "containers",
                "4": "ordinary",
                "5": "reduce",
                "6": "ordinary",
                "7": "comfortable"
            },
            "grammarAnswers": {
                "0": "w",
                "1": "w",
                "2": "w",
                "3": "w",
                "4": "w"
            },
            "comprehensionAnswers": {
                "0": "A piece of paper with homework",
                "1": "Coffee",
                "2": "To reduce waste",
                "3": "Tubes of toothpaste",
                "4": "Sleep and relax"
            },
            "shortAnswers": {
                "0": "w",
                "1": "w",
                "2": "w",
                "3": "w",
                "4": "w"
            }
        },
        "feedback": "Saved for teacher review.",
        "timestamp": "2026-05-25 14:19"
    }
]